setup.py
verihash/__init__.py
verihash.egg-info/PKG-INFO
verihash.egg-info/SOURCES.txt
verihash.egg-info/dependency_links.txt
verihash.egg-info/not-zip-safe
verihash.egg-info/top_level.txt